typehints_checker/__init__.py
typehints_checker/utils.py
typehints_checker-0.0.2.dist-info/LICENSE
typehints_checker-0.0.2.dist-info/METADATA
typehints_checker-0.0.2.dist-info/WHEEL
typehints_checker-0.0.2.dist-info/top_level.txt
typehints_checker-0.0.2.dist-info/RECORD
