Metadata-Version: 2.1
Name: typehints-checker
Version: 0.0.2
Summary: Automatic runtime typecheck. Contribute to GoodManWEN/typehints_checker development by creating an account on GitHub.
Home-page: https://github.com/GoodManWEN/typehints_checker
Author: WEN
License: UNKNOWN
Keywords: typehints_checker
Platform: UNKNOWN
Classifier: Programming Language :: Python :: 3
Classifier: Programming Language :: Python :: 3.7
Classifier: Programming Language :: Python :: 3.8
Classifier: Programming Language :: Python :: 3.9
Classifier: License :: OSI Approved :: MIT License
Classifier: Operating System :: POSIX :: Linux
Classifier: Operating System :: Microsoft :: Windows
Classifier: Framework :: AsyncIO
Requires-Python: >=3.7
Requires-Dist: pipeit (>=0.1.4)
